pdfalign/__init__.py
pdfalign/tableify.py
pdfalign-0.0.5.dist-info/LICENSE
pdfalign-0.0.5.dist-info/METADATA
pdfalign-0.0.5.dist-info/WHEEL
pdfalign-0.0.5.dist-info/top_level.txt
pdfalign-0.0.5.dist-info/RECORD
