Metadata-Version: 2.1
Name: pdfalign
Version: 0.0.5
Summary: pdfalign is a very simple tool to grid align extracted pdf text. This is useful for invoice table extraction or further processing with llms / rag systems
Home-page: https://github.com/y-hesse/pdfalign
Author: yhesse
License: MIT
Classifier: Programming Language :: Python :: 3
Classifier: License :: OSI Approved :: MIT License
Classifier: Operating System :: OS Independent
License-File: LICENSE
Requires-Dist: numpy
Requires-Dist: pandas
Requires-Dist: pymupdf
Requires-Dist: pillow
